moca/__init__.py
moca/version.py
moca/bedoperations/__init__.py
moca/bedoperations/fimo.py
moca/bedoperations/model.py
moca/helpers/__init__.py
moca/helpers/centrimo.py
moca/helpers/configuration_parser.py
moca/helpers/cpu_count.py
moca/helpers/db.py
moca/helpers/encode.py
moca/helpers/exceptions.py
moca/helpers/fasta.py
moca/helpers/filename.py
moca/helpers/job_executor.py
moca/helpers/meme.py
moca/helpers/seqstats.py
moca/helpers/xstr.py
moca/pipeline/__init__.py
moca/pipeline/job_processor.py
moca/plotter/__init__.py
moca/plotter/plotter.py
moca/wigoperations/__init__.py
moca/wigoperations/query.py
moca-0.4.3.dist-info/DESCRIPTION.rst
moca-0.4.3.dist-info/METADATA
moca-0.4.3.dist-info/RECORD
moca-0.4.3.dist-info/WHEEL
moca-0.4.3.dist-info/entry_points.txt
moca-0.4.3.dist-info/metadata.json
moca-0.4.3.dist-info/top_level.txt
scripts/__init__.py
scripts/mocacli.py
