Metadata-Version: 2.0
Name: moca
Version: 0.4.3
Summary: Tool for motif conservation analysis
Home-page: https://github.com/saketkc/moca
Author: Saket Choudhary
Author-email: saketkc@gmail.com
License: ISC
Keywords: moca
Platform: UNKNOWN
Classifier: Development Status :: 4 - Beta
Classifier: Intended Audience :: Developers
Classifier: License :: OSI Approved :: ISC License (ISCL)
Classifier: Natural Language :: English
Classifier: Programming Language :: Python :: 2
Classifier: Programming Language :: Python :: 2.6
Classifier: Programming Language :: Python :: 2.7
Classifier: Programming Language :: Python :: 3.3
Classifier: Programming Language :: Python :: 3.5
Classifier: Topic :: Scientific/Engineering :: Bio-Informatics
Classifier: Topic :: Scientific/Engineering :: Visualization
Classifier: Operating System :: POSIX
Classifier: Operating System :: Unix
Classifier: Operating System :: MacOS
Requires-Dist: biopython (>=1.68)
Requires-Dist: click (>=6.6)
Requires-Dist: click-help-colors (>=0.3)
Requires-Dist: coverage (>=4.2)
Requires-Dist: future (>=0.16.0)
Requires-Dist: matplotlib (>=2.0.0)
Requires-Dist: numpy (>=1.11.3)
Requires-Dist: pandas (>=0.19.2)
Requires-Dist: pyBigWig (>=0.2.8)
Requires-Dist: pybedtools (>=0.7.9)
Requires-Dist: pytest (>=3.0.5)
Requires-Dist: pytest-cov (>=2.4.0)
Requires-Dist: pytest-mpl (>=0.5)
Requires-Dist: scipy (>=0.18.1)
Requires-Dist: seaborn (>=0.7.1)
Requires-Dist: six (>=1.10.0)
Requires-Dist: statsmodels (>=0.6.1)
Requires-Dist: tqdm (>=4.7.2)
